pyalgotrade_tushare/__init__.py
pyalgotrade_tushare/barfeed.py
pyalgotrade_tushare/tools.py
pyalgotrade_tushare-0.1.2.dist-info/METADATA
pyalgotrade_tushare-0.1.2.dist-info/WHEEL
pyalgotrade_tushare-0.1.2.dist-info/entry_points.txt
pyalgotrade_tushare-0.1.2.dist-info/top_level.txt
pyalgotrade_tushare-0.1.2.dist-info/RECORD
