Metadata-Version: 2.1
Name: pyalgotrade-tushare
Version: 0.1.2
Summary: pyalgotrade tushare module
Home-page: https://github.com/bopo/pyalgotrade_tushare
Author: bopo.wang
Author-email: ibopo@126.com
License: MIT license
Keywords: pyalgotrade_tushare
Platform: UNKNOWN
Classifier: Development Status :: 2 - Pre-Alpha
Classifier: Intended Audience :: Developers
Classifier: License :: OSI Approved :: MIT License
Classifier: Natural Language :: English
Classifier: Programming Language :: Python :: 3
Classifier: Programming Language :: Python :: 3.3
Classifier: Programming Language :: Python :: 3.4
Classifier: Programming Language :: Python :: 3.5
Classifier: Programming Language :: Python :: 3.6
Classifier: Programming Language :: Python :: 3.7
Requires-Dist: pyalgotrade
Requires-Dist: tushare
Requires-Dist: pytest
